MANIFEST.in
setup.py
couchforms/__init__.py
couchforms/const.py
couchforms/exceptions.py
couchforms/filters.py
couchforms/getters.py
couchforms/models.py
couchforms/signals.py
couchforms/urls.py
couchforms/util.py
couchforms/views.py
couchforms/xml.py
couchforms.egg-info/PKG-INFO
couchforms.egg-info/SOURCES.txt
couchforms.egg-info/dependency_links.txt
couchforms.egg-info/requires.txt
couchforms.egg-info/top_level.txt
couchforms/_design/filters/devicelogs.js
couchforms/_design/filters/xforms.js
couchforms/_design/util/dates.js
couchforms/_design/views/all_submissions_by_domain/map.js
couchforms/_design/views/all_submissions_by_domain/reduce.js
couchforms/_design/views/by_xmlns/map.js
couchforms/_design/views/by_xmlns/reduce.js
couchforms/_design/views/edits/map.js
couchforms/management/__init__.py
couchforms/management/commands/__init__.py
couchforms/management/commands/post_form.py
couchforms/management/commands/submit_form.py
couchforms/management/commands/submit_forms.py
couchforms/static/couchforms/stylesheets/xforms.css
couchforms/templatetags/__init__.py
couchforms/templatetags/xform_tags.py
couchforms/tests/__init__.py
couchforms/tests/test_archive.py
couchforms/tests/test_auth.py
couchforms/tests/test_bugs.py
couchforms/tests/test_duplicates.py
couchforms/tests/test_edits.py
couchforms/tests/test_meta.py
couchforms/tests/test_namespaces.py
couchforms/tests/test_post.py
couchforms/tests/test_xml.py