Metadata-Version: 1.0
Name: couchforms
Version: 3.0.1
Summary: Dimagi Couch Forms for Django
Home-page: http://www.dimagi.com/
Author: Dimagi
Author-email: dev@dimagi.com
License: UNKNOWN
Platform: UNKNOWN
